{
  "lastVerified": "2026-03-01",
  "leaders": [
    {
      "id": "russell-m-nelson",
      "slug": "russell-m-nelson",
      "name": {
        "full": "Russell Marion Nelson",
        "display": "Russell M. Nelson",
        "last": "Nelson"
      },
      "title": "President of the Church",
      "quorum": "first-presidency",
      "seniority": 1,
      "callingDate": "2018-01-14",
      "birthDate": "1924-09-09",
      "birthPlace": "Salt Lake City, Utah, USA",
      "sourceUrl": "https://www.churchofjesuschrist.org/learn/russell-m-nelson",
      "photo": {
        "filename": "russell-m-nelson.jpg",
        "alt": "President Russell M. Nelson"
      },
      "family": {
        "spouseName": "Wendy Watson Nelson",
        "children": 10
      },
      "preCallingCareer": "Cardiothoracic surgeon; professor at University of Utah School of Medicine",
      "education": [
        "University of Utah (BS, MD)",
        "University of Minnesota (PhD)"
      ],
      "bio": {
        "summary": "Pioneer heart surgeon who became the 17th President of The Church of Jesus Christ of Latter-day Saints.",
        "narrativeFile": "russell-m-nelson"
      },
      "conferenceTalks": [],
      "triviaFacts": []
    },
    {
      "id": "dallin-h-oaks",
      "slug": "dallin-h-oaks",
      "name": {
        "full": "Dallin Harris Oaks",
        "display": "Dallin H. Oaks",
        "last": "Oaks"
      },
      "title": "First Counselor in the First Presidency",
      "quorum": "first-presidency",
      "seniority": 2,
      "callingDate": "2018-01-14",
      "birthDate": "1932-08-12",
      "birthPlace": "Provo, Utah, USA",
      "sourceUrl": "https://www.churchofjesuschrist.org/learn/dallin-h-oaks",
      "photo": {
        "filename": "dallin-h-oaks.jpg",
        "alt": "President Dallin H. Oaks"
      },
      "family": {
        "spouseName": "Kristen McMain Oaks",
        "children": 6
      },
      "preCallingCareer": "Law professor at University of Chicago; President of Brigham Young University; Utah Supreme Court Justice",
      "education": [
        "Brigham Young University (BS)",
        "University of Chicago Law School (JD)"
      ],
      "bio": {
        "summary": "Distinguished legal scholar and former Utah Supreme Court Justice who serves as First Counselor in the First Presidency.",
        "narrativeFile": "dallin-h-oaks"
      },
      "conferenceTalks": [],
      "triviaFacts": []
    },
    {
      "id": "henry-b-eyring",
      "slug": "henry-b-eyring",
      "name": {
        "full": "Henry Bennion Eyring",
        "display": "Henry B. Eyring",
        "last": "Eyring"
      },
      "title": "Second Counselor in the First Presidency",
      "quorum": "first-presidency",
      "seniority": 3,
      "callingDate": "2018-01-14",
      "birthDate": "1933-05-31",
      "birthPlace": "Princeton, New Jersey, USA",
      "sourceUrl": "https://www.churchofjesuschrist.org/learn/henry-b-eyring",
      "photo": {
        "filename": "henry-b-eyring.jpg",
        "alt": "President Henry B. Eyring"
      },
      "family": {
        "spouseName": "Kathleen Johnson Eyring",
        "children": 6
      },
      "preCallingCareer": "Business professor at Stanford University and Ricks College; Ricks College president",
      "education": [
        "University of Utah (BS)",
        "Harvard Business School (MBA, DBA)"
      ],
      "bio": {
        "summary": "Business professor and educator who serves as Second Counselor in the First Presidency.",
        "narrativeFile": "henry-b-eyring"
      },
      "conferenceTalks": [],
      "triviaFacts": []
    },
    {
      "id": "jeffrey-r-holland",
      "slug": "jeffrey-r-holland",
      "name": {
        "full": "Jeffrey Roy Holland",
        "display": "Jeffrey R. Holland",
        "last": "Holland"
      },
      "title": "Acting President of the Quorum of the Twelve Apostles",
      "quorum": "quorum-of-twelve",
      "seniority": 4,
      "callingDate": "1994-06-23",
      "birthDate": "1940-12-03",
      "birthPlace": "St. George, Utah, USA",
      "sourceUrl": "https://www.churchofjesuschrist.org/learn/jeffrey-r-holland",
      "photo": {
        "filename": "jeffrey-r-holland.jpg",
        "alt": "Elder Jeffrey R. Holland"
      },
      "family": {
        "spouseName": "Patricia Terry Holland",
        "children": 3
      },
      "preCallingCareer": "President of Brigham Young University; dean of religious education",
      "education": [
        "Brigham Young University (BA, MA)",
        "Yale University (PhD)"
      ],
      "bio": {
        "summary": "Former President of Brigham Young University who serves as the Acting President of the Quorum of the Twelve Apostles.",
        "narrativeFile": "jeffrey-r-holland"
      },
      "conferenceTalks": [],
      "triviaFacts": []
    },
    {
      "id": "dieter-f-uchtdorf",
      "slug": "dieter-f-uchtdorf",
      "name": {
        "full": "Dieter Friedrich Uchtdorf",
        "display": "Dieter F. Uchtdorf",
        "last": "Uchtdorf"
      },
      "title": "Quorum of the Twelve Apostles",
      "quorum": "quorum-of-twelve",
      "seniority": 5,
      "callingDate": "2004-10-02",
      "birthDate": "1940-11-06",
      "birthPlace": "Ostrava, Czechoslovakia (now Czech Republic)",
      "sourceUrl": "https://www.churchofjesuschrist.org/learn/dieter-f-uchtdorf",
      "photo": {
        "filename": "dieter-f-uchtdorf.jpg",
        "alt": "Elder Dieter F. Uchtdorf"
      },
      "family": {
        "spouseName": "Harriet Reich Uchtdorf",
        "children": 2
      },
      "preCallingCareer": "Commercial airline pilot; chief pilot and senior vice president of Lufthansa German Airlines",
      "education": [
        "Lufthansa Flight Academy"
      ],
      "bio": {
        "summary": "Accomplished international airline pilot who became a member of the Quorum of the Twelve Apostles.",
        "narrativeFile": "dieter-f-uchtdorf"
      },
      "conferenceTalks": [],
      "triviaFacts": []
    },
    {
      "id": "david-a-bednar",
      "slug": "david-a-bednar",
      "name": {
        "full": "David Andrew Bednar",
        "display": "David A. Bednar",
        "last": "Bednar"
      },
      "title": "Quorum of the Twelve Apostles",
      "quorum": "quorum-of-twelve",
      "seniority": 6,
      "callingDate": "2004-10-02",
      "birthDate": "1952-06-15",
      "birthPlace": "Oakland, California, USA",
      "sourceUrl": "https://www.churchofjesuschrist.org/learn/david-a-bednar",
      "photo": {
        "filename": "david-a-bednar.jpg",
        "alt": "Elder David A. Bednar"
      },
      "family": {
        "spouseName": "Susan Robinson Bednar",
        "children": 3
      },
      "preCallingCareer": "Management professor; President of Ricks College and BYU-Idaho",
      "education": [
        "Brigham Young University (BS, MS)",
        "Purdue University (PhD)"
      ],
      "bio": {
        "summary": "Management scholar and university president who serves as a member of the Quorum of the Twelve Apostles.",
        "narrativeFile": "david-a-bednar"
      },
      "conferenceTalks": [],
      "triviaFacts": []
    },
    {
      "id": "quentin-l-cook",
      "slug": "quentin-l-cook",
      "name": {
        "full": "Quentin Lamar Cook",
        "display": "Quentin L. Cook",
        "last": "Cook"
      },
      "title": "Quorum of the Twelve Apostles",
      "quorum": "quorum-of-twelve",
      "seniority": 7,
      "callingDate": "2007-10-06",
      "birthDate": "1940-09-08",
      "birthPlace": "Logan, Utah, USA",
      "sourceUrl": "https://www.churchofjesuschrist.org/learn/quentin-l-cook",
      "photo": {
        "filename": "quentin-l-cook.jpg",
        "alt": "Elder Quentin L. Cook"
      },
      "family": {
        "spouseName": "Mary Gaddie Cook",
        "children": 3
      },
      "preCallingCareer": "Attorney; executive in health care industry",
      "education": [
        "Utah State University (BS)",
        "Stanford Law School (JD)"
      ],
      "bio": {
        "summary": "Attorney and health care executive who serves as a member of the Quorum of the Twelve Apostles.",
        "narrativeFile": "quentin-l-cook"
      },
      "conferenceTalks": [],
      "triviaFacts": []
    },
    {
      "id": "d-todd-christofferson",
      "slug": "d-todd-christofferson",
      "name": {
        "full": "David Todd Christofferson",
        "display": "D. Todd Christofferson",
        "last": "Christofferson"
      },
      "title": "Quorum of the Twelve Apostles",
      "quorum": "quorum-of-twelve",
      "seniority": 8,
      "callingDate": "2008-04-05",
      "birthDate": "1945-01-24",
      "birthPlace": "American Fork, Utah, USA",
      "sourceUrl": "https://www.churchofjesuschrist.org/learn/d-todd-christofferson",
      "photo": {
        "filename": "d-todd-christofferson.jpg",
        "alt": "Elder D. Todd Christofferson"
      },
      "family": {
        "spouseName": "Katherine Jacob Christofferson",
        "children": 5
      },
      "preCallingCareer": "Attorney; banking and financial services executive",
      "education": [
        "Brigham Young University (BA)",
        "Duke University School of Law (JD)"
      ],
      "bio": {
        "summary": "Attorney and banking executive who serves as a member of the Quorum of the Twelve Apostles.",
        "narrativeFile": "d-todd-christofferson"
      },
      "conferenceTalks": [],
      "triviaFacts": []
    },
    {
      "id": "neil-l-andersen",
      "slug": "neil-l-andersen",
      "name": {
        "full": "Neil Linden Andersen",
        "display": "Neil L. Andersen",
        "last": "Andersen"
      },
      "title": "Quorum of the Twelve Apostles",
      "quorum": "quorum-of-twelve",
      "seniority": 9,
      "callingDate": "2009-04-04",
      "birthDate": "1951-08-09",
      "birthPlace": "Pocatello, Idaho, USA",
      "sourceUrl": "https://www.churchofjesuschrist.org/learn/neil-l-andersen",
      "photo": {
        "filename": "neil-l-andersen.jpg",
        "alt": "Elder Neil L. Andersen"
      },
      "family": {
        "spouseName": "Kathy Sue Williams Andersen",
        "children": 4
      },
      "preCallingCareer": "Business executive",
      "education": [
        "Brigham Young University (BS)",
        "Harvard Business School (MBA)"
      ],
      "bio": {
        "summary": "Business executive who serves as a member of the Quorum of the Twelve Apostles.",
        "narrativeFile": "neil-l-andersen"
      },
      "conferenceTalks": [],
      "triviaFacts": []
    },
    {
      "id": "ronald-a-rasband",
      "slug": "ronald-a-rasband",
      "name": {
        "full": "Ronald Alan Rasband",
        "display": "Ronald A. Rasband",
        "last": "Rasband"
      },
      "title": "Quorum of the Twelve Apostles",
      "quorum": "quorum-of-twelve",
      "seniority": 10,
      "callingDate": "2015-10-03",
      "birthDate": "1951-02-06",
      "birthPlace": "Salt Lake City, Utah, USA",
      "sourceUrl": "https://www.churchofjesuschrist.org/learn/ronald-a-rasband",
      "photo": {
        "filename": "ronald-a-rasband.jpg",
        "alt": "Elder Ronald A. Rasband"
      },
      "family": {
        "spouseName": "Melanie Twitchell Rasband",
        "children": 5
      },
      "preCallingCareer": "Business executive in home products industry",
      "education": [
        "University of Utah (BS)"
      ],
      "bio": {
        "summary": "Business executive in the home products industry who serves as a member of the Quorum of the Twelve Apostles.",
        "narrativeFile": "ronald-a-rasband"
      },
      "conferenceTalks": [],
      "triviaFacts": []
    },
    {
      "id": "gary-e-stevenson",
      "slug": "gary-e-stevenson",
      "name": {
        "full": "Gary Eugene Stevenson",
        "display": "Gary E. Stevenson",
        "last": "Stevenson"
      },
      "title": "Quorum of the Twelve Apostles",
      "quorum": "quorum-of-twelve",
      "seniority": 11,
      "callingDate": "2015-10-03",
      "birthDate": "1955-08-06",
      "birthPlace": "Idaho Falls, Idaho, USA",
      "sourceUrl": "https://www.churchofjesuschrist.org/learn/gary-e-stevenson",
      "photo": {
        "filename": "gary-e-stevenson.jpg",
        "alt": "Elder Gary E. Stevenson"
      },
      "family": {
        "spouseName": "Lesa Jean Higbee Stevenson",
        "children": 4
      },
      "preCallingCareer": "Business executive; co-founder and CEO of Icon Health and Fitness",
      "education": [
        "Utah State University (BS)"
      ],
      "bio": {
        "summary": "Co-founder and CEO of Icon Health and Fitness who serves as a member of the Quorum of the Twelve Apostles.",
        "narrativeFile": "gary-e-stevenson"
      },
      "conferenceTalks": [],
      "triviaFacts": []
    },
    {
      "id": "dale-g-renlund",
      "slug": "dale-g-renlund",
      "name": {
        "full": "Dale Gunnar Renlund",
        "display": "Dale G. Renlund",
        "last": "Renlund"
      },
      "title": "Quorum of the Twelve Apostles",
      "quorum": "quorum-of-twelve",
      "seniority": 12,
      "callingDate": "2015-10-03",
      "birthDate": "1952-11-13",
      "birthPlace": "Salt Lake City, Utah, USA",
      "sourceUrl": "https://www.churchofjesuschrist.org/learn/dale-g-renlund",
      "photo": {
        "filename": "dale-g-renlund.jpg",
        "alt": "Elder Dale G. Renlund"
      },
      "family": {
        "spouseName": "Ruth Lybbert Renlund",
        "children": 1
      },
      "preCallingCareer": "Cardiologist; professor at University of Utah School of Medicine",
      "education": [
        "University of Utah (BS)",
        "Johns Hopkins University School of Medicine (MD)"
      ],
      "bio": {
        "summary": "Cardiologist and medical professor who serves as a member of the Quorum of the Twelve Apostles.",
        "narrativeFile": "dale-g-renlund"
      },
      "conferenceTalks": [],
      "triviaFacts": []
    },
    {
      "id": "gerrit-w-gong",
      "slug": "gerrit-w-gong",
      "name": {
        "full": "Gerrit Walter Gong",
        "display": "Gerrit W. Gong",
        "last": "Gong"
      },
      "title": "Quorum of the Twelve Apostles",
      "quorum": "quorum-of-twelve",
      "seniority": 13,
      "callingDate": "2018-03-31",
      "birthDate": "1953-12-23",
      "birthPlace": "Redwood City, California, USA",
      "sourceUrl": "https://www.churchofjesuschrist.org/learn/gerrit-w-gong",
      "photo": {
        "filename": "gerrit-w-gong.jpg",
        "alt": "Elder Gerrit W. Gong"
      },
      "family": {
        "spouseName": "Susan Lindsay Gong",
        "children": 4
      },
      "preCallingCareer": "Foreign service officer; assistant secretary of state; Center for Strategic and International Studies fellow",
      "education": [
        "Brigham Young University (BA)",
        "Oxford University (MA, DPhil — Rhodes Scholar)"
      ],
      "bio": {
        "summary": "Rhodes Scholar and former U.S. State Department official who serves as a member of the Quorum of the Twelve Apostles.",
        "narrativeFile": "gerrit-w-gong"
      },
      "conferenceTalks": [],
      "triviaFacts": []
    },
    {
      "id": "ulisses-soares",
      "slug": "ulisses-soares",
      "name": {
        "full": "Ulisses Soares",
        "display": "Ulisses Soares",
        "last": "Soares"
      },
      "title": "Quorum of the Twelve Apostles",
      "quorum": "quorum-of-twelve",
      "seniority": 14,
      "callingDate": "2018-03-31",
      "birthDate": "1958-10-02",
      "birthPlace": "São Paulo, Brazil",
      "sourceUrl": "https://www.churchofjesuschrist.org/learn/ulisses-soares",
      "photo": {
        "filename": "ulisses-soares.jpg",
        "alt": "Elder Ulisses Soares"
      },
      "family": {
        "spouseName": "Rosana Pontes Soares",
        "children": 3
      },
      "preCallingCareer": "Business executive",
      "education": [
        "Fundação Armando Álvares Penteado (BA)"
      ],
      "bio": {
        "summary": "Brazilian business executive who became the first apostle from Brazil in the Quorum of the Twelve Apostles.",
        "narrativeFile": "ulisses-soares"
      },
      "conferenceTalks": [],
      "triviaFacts": []
    },
    {
      "id": "patrick-kearon",
      "slug": "patrick-kearon",
      "name": {
        "full": "Patrick Kearon",
        "display": "Patrick Kearon",
        "last": "Kearon"
      },
      "title": "Quorum of the Twelve Apostles",
      "quorum": "quorum-of-twelve",
      "seniority": 15,
      "callingDate": "2024-04-06",
      "birthDate": "1961-08-10",
      "birthPlace": "England, United Kingdom",
      "sourceUrl": "https://www.churchofjesuschrist.org/learn/patrick-kearon",
      "photo": {
        "filename": "patrick-kearon.jpg",
        "alt": "Elder Patrick Kearon"
      },
      "family": {
        "spouseName": "Jennifer Brunt Kearon",
        "children": 4
      },
      "preCallingCareer": "Business executive; management consultant",
      "education": [
        "University of Edinburgh (MA)"
      ],
      "bio": {
        "summary": "British business executive and management consultant called as the newest member of the Quorum of the Twelve Apostles in April 2024.",
        "narrativeFile": "patrick-kearon"
      },
      "conferenceTalks": [],
      "triviaFacts": []
    }
  ]
}
